[{
    "url": "#",
    "name": "#id_tool",
    "title": "常用工具集",
    "active": true,
    "template": "#nav_kjj",
    "json": "data/list/tool.json",
    "rest": "/rest/getNav.do?category=tool"
}, {
    "url": "#",
    "name": "#id_kjj",
    "title": "常用框架集",
    "template": "#nav_kjj",
    "json": "data/list/kjj.json",
    "rest": "/rest/getNav.do?category=kjj"
}, {
    "url": "#",
    "name": "#id_bkll",
    "title": "博客列表",
    "template": "#nav_bkll",
    "json": "data/list/bkll.json",
    "rest": "/rest/getNav.do?category=bkll"
}]
